LICENSE.txt
MANIFEST.in
README.rst
setup.cfg
setup.py
deepclas4bio/DatasetManager.py
deepclas4bio/Evaluator.py
deepclas4bio/IPredictor.py
deepclas4bio/IReadDataset.py
deepclas4bio/Measures.py
deepclas4bio/Model.py
deepclas4bio/ModelFactory.py
deepclas4bio/Predictor.py
deepclas4bio/PredictorFactory.py
deepclas4bio/ReadDatasetFolders.py
deepclas4bio/__init__.py
deepclas4bio/commandLine.py
deepclas4bio/evaluate.py
deepclas4bio/listMethods.py
deepclas4bio/predict.py
deepclas4bio/server.py
deepclas4bio.egg-info/PKG-INFO
deepclas4bio.egg-info/SOURCES.txt
deepclas4bio.egg-info/dependency_links.txt
deepclas4bio.egg-info/entry_points.txt
deepclas4bio.egg-info/requires.txt
deepclas4bio.egg-info/top_level.txt
deepclas4bio/Caffe/CaffeFunctions.py
deepclas4bio/Caffe/CaffeModel.py
deepclas4bio/Caffe/CaffePredictor.py
deepclas4bio/Caffe/__init__.py
deepclas4bio/DL4J/DL4JFunctions.py
deepclas4bio/DL4J/DL4JModel.py
deepclas4bio/DL4J/DL4JPredictor.py
deepclas4bio/DL4J/__init__.py
deepclas4bio/Fastai/FastaiFunctions.py
deepclas4bio/Fastai/FastaiModel.py
deepclas4bio/Fastai/FastaiPredictor.py
deepclas4bio/Fastai/__init__.py
deepclas4bio/Keras/KerasFunctions.py
deepclas4bio/Keras/KerasModel.py
deepclas4bio/Keras/KerasPredictor.py
deepclas4bio/Keras/__init__.py
deepclas4bio/MxNet/MxNetFunctions.py
deepclas4bio/MxNet/MxNetModel.py
deepclas4bio/MxNet/MxNetPredictor.py
deepclas4bio/MxNet/__init__.py
deepclas4bio/PyTorch/PyTorchFunctions.py
deepclas4bio/PyTorch/PyTorchModel.py
deepclas4bio/PyTorch/PyTorchPredictor.py
deepclas4bio/PyTorch/__init__.py
deepclas4bio/PyTorch/Classification/__init__.py
deepclas4bio/PyTorch/Classification/model/ResNet34Kvasir.py
deepclas4bio/PyTorch/Classification/model/__init__.py