Metadata-Version: 1.1
Name: deepclas4bio
Version: 0.0.35
Summary: API that provides a common acces point for classification models of several deep learning frameworks.
Home-page: https://github.com/adines/DeepClas4Bio
Author: Adrian Ines
Author-email: adines@unirioja.es
License: UNKNOWN
Keywords: classification,frameworks,deep learning,interoperability
Platform: UNKNOWN
Classifier: Development Status :: 4 - Beta
Classifier: Intended Audience :: Developers
Classifier: Topic :: Software Development :: Build Tools
Classifier: License :: OSI Approved :: MIT License
Classifier: Programming Language :: Python :: 3.6
